padocc/__init__.py
padocc/cli.py
padocc/core/__init__.py
padocc/core/catalog.py
padocc/core/errors.py
padocc/core/filehandlers.py
padocc/core/logs.py
padocc/core/mixins/__init__.py
padocc/core/mixins/dataset.py
padocc/core/mixins/directory.py
padocc/core/mixins/properties.py
padocc/core/mixins/status.py
padocc/core/project.py
padocc/core/utils.py
padocc/design.md
padocc/groups/__init__.py
padocc/groups/group.py
padocc/groups/mixins/__init__.py
padocc/groups/mixins/allocations.py
padocc/groups/mixins/evaluations.py
padocc/groups/mixins/initialisation.py
padocc/groups/mixins/modifiers.py
padocc/groups/shepard.py
padocc/phases/__init__.py
padocc/phases/aggregate.py
padocc/phases/compute.py
padocc/phases/ingest.py
padocc/phases/scan.py
padocc/phases/validate.py
padocc/shell.py
padocc/temp.txt
padocc/tests/conftest.py
padocc/tests/data/example_validation_report.yaml
padocc/tests/data/myfile.csv
padocc/tests/data/rain/example1.0.nc
padocc/tests/data/rain/example1.1.nc
padocc/tests/data/rain/example1.2.nc
padocc/tests/data/rain/example1.3.nc
padocc/tests/data/rain/example1.4.nc
padocc/tests/data/rain/example2.0.nc
padocc/tests/data/rain/example2.1.nc
padocc/tests/data/rain/example2.2.nc
padocc/tests/data/rain/example2.3.nc
padocc/tests/data/rain/example2.4.nc
padocc/tests/data/test1.txt
padocc/tests/data/test2.txt
padocc/tests/data_creator/0DAgg/rem.json
padocc/tests/data_creator/1DAgg/file0.nc
padocc/tests/data_creator/1DAgg/file1.nc
padocc/tests/data_creator/1DAgg/file2.nc
padocc/tests/data_creator/1DAgg/file3.nc
padocc/tests/data_creator/1DAgg/file4.nc
padocc/tests/data_creator/1DAgg/file5.nc
padocc/tests/data_creator/1DAgg/file6.nc
padocc/tests/data_creator/1DAgg/file7.nc
padocc/tests/data_creator/3DAgg/file0.nc
padocc/tests/data_creator/3DAgg/file1.nc
padocc/tests/data_creator/3DAgg/file2.nc
padocc/tests/data_creator/3DAgg/file3.nc
padocc/tests/data_creator/3DAgg/file4.nc
padocc/tests/data_creator/3DAgg/file5.nc
padocc/tests/data_creator/3DAgg/file6.nc
padocc-1.4.5.dist-info/LICENSE
padocc-1.4.5.dist-info/METADATA
padocc-1.4.5.dist-info/WHEEL
padocc-1.4.5.dist-info/entry_points.txt
padocc-1.4.5.dist-info/RECORD
