Metadata-Version: 2.3
Name: padocc
Version: 1.4.5
Summary: Pipeline to Aggregate Data for Optimised Cloud Capabilities
License: BSD 3
Author: Daniel Westwood
Author-email: daniel.westwood@stfc.ac.uk
Requires-Python: >=3.11,<4.0
Classifier: License :: Other/Proprietary License
Classifier: Programming Language :: Python :: 3
Classifier: Programming Language :: Python :: 3.11
Classifier: Programming Language :: Python :: 3.12
Classifier: Programming Language :: Python :: 3.13
Requires-Dist: aiohttp (>=3.10.10,<4.0.0)
Requires-Dist: binpacking (>=1.5.2,<2.0.0)
Requires-Dist: cfapyx (>=2025.12.9)
Requires-Dist: cfgrib (==0.9.14.1)
Requires-Dist: dask (>=2025.11.0,<2026)
Requires-Dist: distributed (>=2025.11.0,<2026)
Requires-Dist: elasticsearch (>=8.0.0,<9.0.0)
Requires-Dist: fsspec (>=2025.7,<2026.0)
Requires-Dist: h5py (>=3.11.0,<4.0.0)
Requires-Dist: kerchunk (>=0.2.9,<0.3.0)
Requires-Dist: matplotlib (==3.9.2)
Requires-Dist: myst-nb (>=1.1.2,<2.0.0)
Requires-Dist: netcdf4 (>=1.7.2,<2.0.0)
Requires-Dist: numpy (<=3.0.0)
Requires-Dist: pytest (>=8.3.5,<9.0.0)
Requires-Dist: rechunker (==0.5.2)
Requires-Dist: requests (>=2.32.3,<3.0.0)
Requires-Dist: s3fs (>=2025.7.0,<2026.0.0)
Requires-Dist: scipy (>=1.12.0,<2.0.0)
Requires-Dist: tifffile (>=2024.9.20,<2025.0.0)
Requires-Dist: types-pyyaml (>=6.0.12.20240917,<7.0.0.0)
Requires-Dist: virtualizarr (>=2.0.1)
Requires-Dist: xarray (>=2024,<2026)
Requires-Dist: zarr (>=2.18.4)
